{"cameraMode":{"drawMode":0,"name":"Shaded","section":"Shading Mode"},"sceneLighting":true,"audioPlay":false,"sceneViewState":{"m_AlwaysRefresh":false,"showFog":true,"showSkybox":true,"showFlares":true,"showImageEffects":true,"showParticleSystems":true,"showVisualEffectGraphs":true,"m_FxEnabled":true},"in2DMode":false,"pivot":{"x":7.2821807861328129,"y":-5.891798973083496,"z":-2.314846992492676},"rotation":{"x":0.13678579032421113,"y":-0.8627148866653442,"z":0.32799163460731509,"w":0.35978344082832339},"size":28.790142059326173,"orthographic":false}